[
  {
    "id": "AGENTS.md::0",
    "source": "AGENTS.md",
    "content": "# Andrews-Method Knowledge Base ## Структура ``` Andrews-Method/ ├── atomic/ # Атомарные заметки (один концепт) │ ├── 001-median-line.md │ ├── 002-pitchfork.md │ ├── 031-ar1-linea-centro.md │ ├── 041-ar2-action-line.md │ ├── 054-new-forks-rule1.md │ ├── 080-median-pivot-zone.md │ ├── 092-ar3-horizontal.md │ └── 095-super-pitchforks.md │ ├── synthetic/ # Синтетические заметки (объединение концептов) │ ├── philosophy-and-methods.md │ ├── momentum-swing.md │ └── high-low-lines.md │ ├── indexes/ # Индексы и",
    "tags": [],
    "links": [],
    "chunk_index": 0,
    "total_chunks": 3,
    "title": "AGENTS"
  },
  {
    "id": "AGENTS.md::1",
    "source": "AGENTS.md",
    "content": "навигация │ ├── 📅-timeline.md │ └── 🏷️-tags.md │ └── examples/ # Примеры на реальных активах └── (файлы примеров) ``` ## Zettelkasten принципы 1. **Атомарность** — одна идея на заметку 2. **Связи** — ссылки на связанные заметки 3. **Теги** — для навигации и RAG 4. **Автономность** — заметка читается без контекста ## RAG Integration Для использования в AstroFin Sentinel: ``` knowledge_base = \"/home/workspace/Knowledge/Andrews-Method\" index_name = \"andrews-method\" chunk_size = 512 ``` ## Источники - Патрик",
    "tags": [],
    "links": [],
    "chunk_index": 1,
    "total_chunks": 3,
    "title": "AGENTS"
  },
  {
    "id": "AGENTS.md::2",
    "source": "AGENTS.md",
    "content": "Микула \"Лучшие методы линий тренда Алана Эндрюса плюс пять новых техник\" - Материалы Google Drive папки \"ТРЕЙД\"",
    "tags": [],
    "links": [],
    "chunk_index": 2,
    "total_chunks": 3,
    "title": "AGENTS"
  },
  {
    "id": "atomic/001-median-line.md::0",
    "source": "atomic/001-median-line.md",
    "content": "# 001: Срединная линия (Median Line) ## Конспект **Суть:** Срединная линия — это линия, проведённая от разворотной точки **A** через середину отрезка **B-C**, где B и C — экстремумы колебания. **Ключевое свойство:** Эндрюс утверждал, что цена достигает Срединной линии в **~80% случаев**. ## Построение ``` 1. Найти три разворотные точки: A (начало), B (максимум/минимум), C (противоположный экстремум) 2. Провести линию от A через середину BC 3. Это и есть Срединная линия ``` ``` B /|\\ / | \\ / | \\ / | \\ / | \\",
    "tags": [
      "#СрединнаяЛиния",
      "#Равновесие",
      "#ТехническийАнализ",
      "#Основа",
      "#Эндрюс"
    ],
    "links": [
      "002-pitchfork",
      "003-signal-lines",
      "080-median-pivot-zone",
      "095-super-pitchforks"
    ],
    "chunk_index": 0,
    "total_chunks": 3,
    "title": "001-median-line"
  },
  {
    "id": "atomic/001-median-line.md::1",
    "source": "atomic/001-median-line.md",
    "content": "A-----|-----C ↑ Срединная линия ``` ## Физический смысл - Срединная линия представляет \"линию равновесия\" колебания - Цена стремится вернуться к равновесию (как маятник) - Это **магнит цены** ## Правила торговли | Правило | Условие | Действие | |---------|---------|----------| | 1 | Цена идёт к медиане | Ждать признаков разворота | | 2 | Цена не дошла и развернулась | Цель = предыдущий экстремум | | 3 | Цена пробила медиану | Ожидать движения к противоположной параллели | ## Теги `#СрединнаяЛиния` `#Основа`",
    "tags": [
      "#СрединнаяЛиния",
      "#Равновесие",
      "#ТехническийАнализ",
      "#Основа",
      "#Эндрюс"
    ],
    "links": [
      "002-pitchfork",
      "003-signal-lines",
      "080-median-pivot-zone",
      "095-super-pitchforks"
    ],
    "chunk_index": 1,
    "total_chunks": 3,
    "title": "001-median-line"
  },
  {
    "id": "atomic/001-median-line.md::2",
    "source": "atomic/001-median-line.md",
    "content": "`#Эндрюс` `#ТехническийАнализ` `#Равновесие` ## Связи - [[002-pitchfork|📊 Вилы Эндрюса]] — развитие концепции - [[003-signal-lines|📶 Сигнальные линии]] — параллели к медиане - [[080-median-pivot-zone|⏱️ Разворотная Зона]] — временная оценка - [[095-super-pitchforks|🚀 Супер-Вилы]] — объединение с A-R",
    "tags": [
      "#СрединнаяЛиния",
      "#Равновесие",
      "#ТехническийАнализ",
      "#Основа",
      "#Эндрюс"
    ],
    "links": [
      "002-pitchfork",
      "003-signal-lines",
      "080-median-pivot-zone",
      "095-super-pitchforks"
    ],
    "chunk_index": 2,
    "total_chunks": 3,
    "title": "001-median-line"
  },
  {
    "id": "atomic/002-pitchfork.md::0",
    "source": "atomic/002-pitchfork.md",
    "content": "# 002: Вилы Эндрюса (Andrews Pitchfork) ## Конспект **Суть:** Вилы — это канал, образованный Срединной линией и двумя параллельными линиями, проведёнными через точки B и C. ## Построение ``` 1. Провести Срединную линию от A через середину BC 2. Через точку B провести линию, параллельную медиане 3. Через точку C провести линию, параллельную медиане ``` ``` B--------|------- B (параллель) /| | / / | | / | / | | / | / | | / | A----|--- C --|----A C ↑ медиана Срединная линия ``` ## Компоненты | Компонент |",
    "tags": [
      "#Канал",
      "#ТехническийАнализ",
      "#Вилы",
      "#Эндрюс",
      "#Pitchfork"
    ],
    "links": [
      "001-median-line",
      "003-signal-lines",
      "054-new-forks-rule1",
      "095-super-pitchforks"
    ],
    "chunk_index": 0,
    "total_chunks": 3,
    "title": "002-pitchfork"
  },
  {
    "id": "atomic/002-pitchfork.md::1",
    "source": "atomic/002-pitchfork.md",
    "content": "Описание | |-----------|----------| | **Срединная линия** | Центральная линия (магнит цены) | | **Верхняя параллель** | Линия через B | | **Нижняя параллель** | Линия через C | | **Ширина вил** | Расстояние между B и C | ## Сигнальные линии (Trigger Lines) Дополнительные линии внутри вил: - **Верхняя сигнальная** — 1/2 ширины сверху - **Нижняя сигнальная** — 1/2 ширины снизу ## Теги `#Вилы` `#Pitchfork` `#Канал` `#Эндрюс` `#ТехническийАнализ` ## Связи - [[001-median-line|📐 Срединная линия]] — основа -",
    "tags": [
      "#Канал",
      "#ТехническийАнализ",
      "#Вилы",
      "#Эндрюс",
      "#Pitchfork"
    ],
    "links": [
      "001-median-line",
      "003-signal-lines",
      "054-new-forks-rule1",
      "095-super-pitchforks"
    ],
    "chunk_index": 1,
    "total_chunks": 3,
    "title": "002-pitchfork"
  },
  {
    "id": "atomic/002-pitchfork.md::2",
    "source": "atomic/002-pitchfork.md",
    "content": "[[003-signal-lines|📶 Сигнальные линии]] - [[054-new-forks-rule1|🔧 Новые Вилы]] - [[095-super-pitchforks|🚀 Супер-Вилы]]",
    "tags": [
      "#Канал",
      "#ТехническийАнализ",
      "#Вилы",
      "#Эндрюс",
      "#Pitchfork"
    ],
    "links": [
      "001-median-line",
      "003-signal-lines",
      "054-new-forks-rule1",
      "095-super-pitchforks"
    ],
    "chunk_index": 2,
    "total_chunks": 3,
    "title": "002-pitchfork"
  },
  {
    "id": "atomic/031-ar1-linea-centro.md::0",
    "source": "atomic/031-ar1-linea-centro.md",
    "content": "# 031: Метод Действия-Реакции 1 — Линия Центра ## Конспект **Суть:** Множество линий **действия** (слева от центра) проецируются как линии **реакции** (справа). ## Построение ``` 1. Определить разворотные точки на графике 2. Провести линию действия через значимые экстремумы 3. Спроецировать линии реакции параллельно в будущее ``` ## Принцип - Каждый исторический экстремум ищет свою \"реакцию\" в будущем - Линии реакции = будущие зоны поддержки/сопротивления - **RL1, RL2, RL3...** — линии реакции на разных",
    "tags": [
      "#ActionReaction",
      "#ЛинияЦентра",
      "#Проекция",
      "#ДействиеРеакция",
      "#A"
    ],
    "links": [
      "041-ar2-action-line",
      "092-ar3-horizontal",
      "095-super-pitchforks"
    ],
    "chunk_index": 0,
    "total_chunks": 2,
    "title": "031-ar1-linea-centro"
  },
  {
    "id": "atomic/031-ar1-linea-centro.md::1",
    "source": "atomic/031-ar1-linea-centro.md",
    "content": "расстояниях ## Отличие от метода 2 | Метод 1 | Метод 2 | |---------|---------| | Множество линий действия | Одна линия действия | | Каждая проецируется как реакция | Одна линия → множество RL (RL1, RL2, RL3...) | | Более прямолинейно | Более компактно | ## Теги `#ДействиеРеакция` `#ActionReaction` `#A-R1` `#ЛинияЦентра` `#Проекция` ## Связи - [[041-ar2-action-line|② Метод A-R 2: Линия Действия]] - [[092-ar3-horizontal|③ Метод A-R 3: Горизонтальные уровни]] - [[095-super-pitchforks|🚀 Супер-Вилы]]",
    "tags": [
      "#ActionReaction",
      "#ЛинияЦентра",
      "#Проекция",
      "#ДействиеРеакция",
      "#A"
    ],
    "links": [
      "041-ar2-action-line",
      "092-ar3-horizontal",
      "095-super-pitchforks"
    ],
    "chunk_index": 1,
    "total_chunks": 2,
    "title": "031-ar1-linea-centro"
  },
  {
    "id": "atomic/095-super-pitchforks.md::0",
    "source": "atomic/095-super-pitchforks.md",
    "content": "# 095: Супер-Вилы (Super Pitchforks) ## Конспект **Суть:** Объединение **Вил Эндрюса** и **Метода Действия-Реакции** для получения более надёжных сигналов на пересечении линий. > *\"Линии Реакции, проведенные по последним данным, работали лучше всего\"* ## Построение ``` 1. Строим стандартные Вилы по точкам A, B, C 2. Линия B-C используется как Линия Центра для A-R 3. Расстояние от A до линии B-C = шаг для линий реакции 4. Проводим линии реакции (RL1, RL2, RL3...) параллельно линии B-C ``` ## Ключевая точка",
    "tags": [
      "#ПересечениеЛиний",
      "#Микула",
      "#SuperPitchfork",
      "#Эндрюс",
      "#Синтез",
      "#СуперВилы"
    ],
    "links": [
      "Супер-Вилы – пример на Qualcomm",
      "Супер-Вилы – пример на Eli Lilly",
      "Супер-Вилы – пример на Network Associates",
      "001-median-line",
      "002-pitchfork",
      "031-ar1-linea-centro",
      "041-ar2-action-line",
      "092-ar3-horizontal"
    ],
    "chunk_index": 0,
    "total_chunks": 3,
    "title": "095-super-pitchforks"
  },
  {
    "id": "atomic/095-super-pitchforks.md::1",
    "source": "atomic/095-super-pitchforks.md",
    "content": "D **Пересечение Срединной линии + Линии реакции 1 = зона высокого потенциала** ``` RL2 / RL1/------- D (пересечение медианы и RL1) / / A---/--- B \\ \\----- C \\ RL1 ``` ## Сигналы Супервил | Сигнал | Описание | |--------|----------| | **Точка D** | Пересечение медианы и RL1 — искать разворот | | **RL + Warning Line** | Пересечение линии реакции и предупреждающей линии | | **Шип на медиане** | Резкое касание и отскок | ## Примеры - [[Супер-Вилы – пример на Qualcomm|Qualcomm (QCOM)]] - [[Супер-Вилы – пример на",
    "tags": [
      "#ПересечениеЛиний",
      "#Микула",
      "#SuperPitchfork",
      "#Эндрюс",
      "#Синтез",
      "#СуперВилы"
    ],
    "links": [
      "Супер-Вилы – пример на Qualcomm",
      "Супер-Вилы – пример на Eli Lilly",
      "Супер-Вилы – пример на Network Associates",
      "001-median-line",
      "002-pitchfork",
      "031-ar1-linea-centro",
      "041-ar2-action-line",
      "092-ar3-horizontal"
    ],
    "chunk_index": 1,
    "total_chunks": 3,
    "title": "095-super-pitchforks"
  },
  {
    "id": "atomic/095-super-pitchforks.md::2",
    "source": "atomic/095-super-pitchforks.md",
    "content": "Eli Lilly|Eli Lilly]] - [[Супер-Вилы – пример на Network Associates|Network Associates]] ## Теги `#СуперВилы` `#SuperPitchfork` `#Синтез` `#ПересечениеЛиний` `#Эндрюс` `#Микула` ## Связи - [[001-median-line|📐 Срединная линия]] - [[002-pitchfork|📊 Вилы Эндрюса]] - [[031-ar1-linea-centro|① Метод A-R 1]] - [[041-ar2-action-line|② Метод A-R 2]] - [[092-ar3-horizontal|③ Метод A-R 3]]",
    "tags": [
      "#ПересечениеЛиний",
      "#Микула",
      "#SuperPitchfork",
      "#Эндрюс",
      "#Синтез",
      "#СуперВилы"
    ],
    "links": [
      "Супер-Вилы – пример на Qualcomm",
      "Супер-Вилы – пример на Eli Lilly",
      "Супер-Вилы – пример на Network Associates",
      "001-median-line",
      "002-pitchfork",
      "031-ar1-linea-centro",
      "041-ar2-action-line",
      "092-ar3-horizontal"
    ],
    "chunk_index": 2,
    "total_chunks": 3,
    "title": "095-super-pitchforks"
  },
  {
    "id": "atomic/080-median-pivot-zone.md::0",
    "source": "atomic/080-median-pivot-zone.md",
    "content": "# 080: Разворотная Зона Срединной Линии (Median Line Pivot Zone) ## Конспект **Суть:** Инструмент для оценки **времени** достижения ценой Срединной линии. > *\"Как долго трейдер должен ждать, пока цена дойдет до Медианы?\"* ## Построение ``` 1. Провести Срединную линию (A, B, C) 2. Посчитать количество баров: A→B и B→C 3. Взять БОЛЬШЕЕ значение 4. От точки C отложить это количество баров вперёд по медиане 5. Построить прямоугольник от C до этой точки ``` ``` |←── 15 bars (max) ──→|",
    "tags": [
      "#Время",
      "#Микула",
      "#Цикличность",
      "#Медиана",
      "#РазворотнаяЗона",
      "#Эндрюс"
    ],
    "links": [
      "001-median-line",
      "momentum-swing"
    ],
    "chunk_index": 0,
    "total_chunks": 3,
    "title": "080-median-pivot-zone"
  },
  {
    "id": "atomic/080-median-pivot-zone.md::1",
    "source": "atomic/080-median-pivot-zone.md",
    "content": "C───────────────────[POINT] │ ↑ │ 矩形 = Разворотная Зона ↓ ``` ## Интерпретация | Условие | Значение | |---------|----------| | Цена коснулась медианы **внутри зоны** | Рынок в цикличном режиме — можно торговать | | Цена **не достигла** медианы | Рынок не в фазе — осторожность | | **Множественные касания** | Не входить на первом касании | ## Правила - ⚠️ Касание **не гарантирует** разворот - ✅ Касание **подтверждает** цикличный режим - ⏱️ Зона = временной ориентир, а не точное время ## Теги",
    "tags": [
      "#Время",
      "#Микула",
      "#Цикличность",
      "#Медиана",
      "#РазворотнаяЗона",
      "#Эндрюс"
    ],
    "links": [
      "001-median-line",
      "momentum-swing"
    ],
    "chunk_index": 1,
    "total_chunks": 3,
    "title": "080-median-pivot-zone"
  },
  {
    "id": "atomic/080-median-pivot-zone.md::2",
    "source": "atomic/080-median-pivot-zone.md",
    "content": "`#РазворотнаяЗона` `#Время` `#Цикличность` `#Медиана` `#Эндрюс` `#Микула` ## Связи - [[001-median-line|📐 Срединная линия]] - [[momentum-swing|📈 Momentum Swing]]",
    "tags": [
      "#Время",
      "#Микула",
      "#Цикличность",
      "#Медиана",
      "#РазворотнаяЗона",
      "#Эндрюс"
    ],
    "links": [
      "001-median-line",
      "momentum-swing"
    ],
    "chunk_index": 2,
    "total_chunks": 3,
    "title": "080-median-pivot-zone"
  },
  {
    "id": "synthetic/philosophy-and-methods.md::0",
    "source": "synthetic/philosophy-and-methods.md",
    "content": "# Философия и методы линий тренда ## Дайджест: от Ганна до Супервил **Дата:** 26 февраля 2026 **Автор:** Совместное исследование (User + AI) ## Ключевые концепции ### 1. Срединная линия — \"магнит цены\" - Основа вил Эндрюса - **80% случаев** цена возвращается к медиане - Построение: от A через середину BC ### 2. Вилы Эндрюса и Сигнальные линии - Канал, образованный медианой + параллели через B и C - Пробой параллели = сигнал к входу ### 3. Предупреждающие линии (Warning Lines) - Дополнительные параллели с",
    "tags": [
      "#Дайджест",
      "#Микула",
      "#ЛинииТренда",
      "#ТехническийАнализ",
      "#ФилософияТрейдинга",
      "#Эндрюс",
      "#Ганн"
    ],
    "links": [
      "Уильям Ганн: геометрия и астрология",
      "Финансовая астрология в инвестициях",
      "AstroFin Sentinel"
    ],
    "chunk_index": 0,
    "total_chunks": 5,
    "title": "philosophy-and-methods"
  },
  {
    "id": "synthetic/philosophy-and-methods.md::1",
    "source": "synthetic/philosophy-and-methods.md",
    "content": "тем же шагом - Сетка уровней поддержки/сопротивления ### 4. Методы Действия-Реакции - **Метод 1:** Множество линий действия → линии реакции - **Метод 2:** Одна линия действия → RL1, RL2, RL3... - **Метод 3:** Горизонтальные уровни от первого отката ### 5. Разворотная Зона Срединной линии - Временная оценка достижения медианы - Подтверждение цикличного режима ### 6. Супервилы - Объединение вил и A-R - Пересечение линий = зона высокого потенциала ## Торговые сигналы (сводка) | Концепция | Сигнал | Действие |",
    "tags": [
      "#Дайджест",
      "#Микула",
      "#ЛинииТренда",
      "#ТехническийАнализ",
      "#ФилософияТрейдинга",
      "#Эндрюс",
      "#Ганн"
    ],
    "links": [
      "Уильям Ганн: геометрия и астрология",
      "Финансовая астрология в инвестициях",
      "AstroFin Sentinel"
    ],
    "chunk_index": 1,
    "total_chunks": 5,
    "title": "philosophy-and-methods"
  },
  {
    "id": "synthetic/philosophy-and-methods.md::2",
    "source": "synthetic/philosophy-and-methods.md",
    "content": "|-----------|--------|----------| | Возврат к медиане | Касание внутри Разворотной зоны | Искать разворотный паттерн | | Недостижение медианы | Разворот до линии | Цель = предыдущий экстремум | | Пробой сигнальной | Бар полностью выше/ниже | Вход в направлении пробоя | | Пересечение (Супервилы) | Медиана + RL1 | Зона разворота | ## Философия > *\"Трейдер предполагает, что рынок находится в циклическом режиме и ждёт признаков верхней разворотной точки\"* ### Ключевые принципы 1. **Рынок цикличен** — наша",
    "tags": [
      "#Дайджест",
      "#Микула",
      "#ЛинииТренда",
      "#ТехническийАнализ",
      "#ФилософияТрейдинга",
      "#Эндрюс",
      "#Ганн"
    ],
    "links": [
      "Уильям Ганн: геометрия и астрология",
      "Финансовая астрология в инвестициях",
      "AstroFin Sentinel"
    ],
    "chunk_index": 2,
    "total_chunks": 5,
    "title": "philosophy-and-methods"
  },
  {
    "id": "synthetic/philosophy-and-methods.md::3",
    "source": "synthetic/philosophy-and-methods.md",
    "content": "задача идентифицировать фазу 2. **Ожидание** — касание уровня ≠ сигнал, нужно подтверждение 3. **Пересечения** — объединяют два независимых расчёта 4. **Дисциплина** — следуем правилам, а не эмоциям ### Смещение фокуса С **\"как сделать\"** → На **\"что создать\"** - Создаём структуру, где хаос обретает порядок - Создаём вероятностные зоны, а не жёсткие предсказания - Создаём объективные ориентиры для субъективного опыта ## Связи - [[Уильям Ганн: геометрия и астрология]] - [[Финансовая астрология в",
    "tags": [
      "#Дайджест",
      "#Микула",
      "#ЛинииТренда",
      "#ТехническийАнализ",
      "#ФилософияТрейдинга",
      "#Эндрюс",
      "#Ганн"
    ],
    "links": [
      "Уильям Ганн: геометрия и астрология",
      "Финансовая астрология в инвестициях",
      "AstroFin Sentinel"
    ],
    "chunk_index": 3,
    "total_chunks": 5,
    "title": "philosophy-and-methods"
  },
  {
    "id": "synthetic/philosophy-and-methods.md::4",
    "source": "synthetic/philosophy-and-methods.md",
    "content": "инвестициях]] - [[AstroFin Sentinel]] ## Теги `#Дайджест` `#Эндрюс` `#Ганн` `#Микула` `#ТехническийАнализ` `#ЛинииТренда` `#ФилософияТрейдинга`",
    "tags": [
      "#Дайджест",
      "#Микула",
      "#ЛинииТренда",
      "#ТехническийАнализ",
      "#ФилософияТрейдинга",
      "#Эндрюс",
      "#Ганн"
    ],
    "links": [
      "Уильям Ганн: геометрия и астрология",
      "Финансовая астрология в инвестициях",
      "AstroFin Sentinel"
    ],
    "chunk_index": 4,
    "total_chunks": 5,
    "title": "philosophy-and-methods"
  },
  {
    "id": "indexes/📅-timeline.md::0",
    "source": "indexes/📅-timeline.md",
    "content": "# Timeline: Методы Эндрюса ## Концепции (от простого к сложному) ```timeline [6] Срединная линия - основа [7] Теория Срединной линии [8] Принципы торговли 1-3 [14] Сигнальные линии [31] Метод Действия-Реакции 1 (Линия Центра) [41] Метод Действия-Реакции 2 (Линия Действия) [54] Новые Вилы - Правило торговли 1 [80] Разворотная Зона Срединной Линии [92] Метод Действия-Реакции 3 (горизонтальные уровни) [95] Супер-Вилы ``` ## Ключевые идеи | Концепция | Теги | Связь | |-----------|------|-------| | Срединная",
    "tags": [
      "#ТорговляПоМедиане",
      "#ЛинияЦентра",
      "#ПредупреждающиеЛинии",
      "#Pitchfork",
      "#MomentumSwing",
      "#Микула",
      "#СвинговаяТорговля",
      "#Цикличность",
      "#ТехническийАнализ",
      "#ЛинияДействия",
      "#Основа",
      "#РазворотнаяЗона",
      "#Вилы",
      "#Синтез",
      "#СрединнаяЛиния",
      "#WarningLines",
      "#Время",
      "#ГоризонтальныеУровни",
      "#НовыеВилы",
      "#Медиана",
      "#ДействиеРеакция",
      "#A",
      "#СигнальныеЛинии",
      "#Стратегия",
      "#МетодЭндрюса",
      "#Тренд",
      "#СуперВилы"
    ],
    "links": [],
    "chunk_index": 0,
    "total_chunks": 4,
    "title": "📅-timeline"
  },
  {
    "id": "indexes/📅-timeline.md::1",
    "source": "indexes/📅-timeline.md",
    "content": "линия | `#СрединнаяЛиния` `#Основа` | Вилы, все методы | | Вилы Эндрюса | `#Вилы` `#Pitchfork` | Сигнальные линии, Супервилы | | Метод Действия-Реакции | `#ДействиеРеакция` `#A-R` | Линии реакции, RL1/2/3 | | Разворотная Зона | `#РазворотнаяЗона` `#Время` | Цикличность | | Супервилы | `#СуперВилы` `#Синтез` | Объединяет Вилы + Действие-Реакция | | Предупреждающие линии | `#WarningLines` | Вилы, тренд | | Momentum Swing | `#MomentumSwing` `#Стратегия` | Торговля по медиане | ## Связи между методами ```",
    "tags": [
      "#ТорговляПоМедиане",
      "#ЛинияЦентра",
      "#ПредупреждающиеЛинии",
      "#Pitchfork",
      "#MomentumSwing",
      "#Микула",
      "#СвинговаяТорговля",
      "#Цикличность",
      "#ТехническийАнализ",
      "#ЛинияДействия",
      "#Основа",
      "#РазворотнаяЗона",
      "#Вилы",
      "#Синтез",
      "#СрединнаяЛиния",
      "#WarningLines",
      "#Время",
      "#ГоризонтальныеУровни",
      "#НовыеВилы",
      "#Медиана",
      "#ДействиеРеакция",
      "#A",
      "#СигнальныеЛинии",
      "#Стратегия",
      "#МетодЭндрюса",
      "#Тренд",
      "#СуперВилы"
    ],
    "links": [],
    "chunk_index": 1,
    "total_chunks": 4,
    "title": "📅-timeline"
  },
  {
    "id": "indexes/📅-timeline.md::2",
    "source": "indexes/📅-timeline.md",
    "content": "СрединнаяЛиния ──┬── ВилыЭндрюса ──┬── СигнальныеЛинии │ ├── НовыеВилы │ └── СуперВилы ├── ПредупреждающиеЛинии └── РазворотнаяЗона МетодыДействияРеакции ──┬── АctionReaction1 (ЛинияЦентра) ├── ActionReaction2 (ЛинияДействия) ├── ActionReaction3 (Горизонтальные) └── СуперВилы (объединение) ``` ## Теги (alphabetical) #Вилы #ГоризонтальныеУровни #ДействиеРеакция #ЛинияЦентра #ЛинияДействия #Медиана #МетодЭндрюса #Микула #НовыеВилы #ПредупреждающиеЛинии #РазворотнаяЗона #СвинговаяТорговля #СигнальныеЛинии",
    "tags": [
      "#ТорговляПоМедиане",
      "#ЛинияЦентра",
      "#ПредупреждающиеЛинии",
      "#Pitchfork",
      "#MomentumSwing",
      "#Микула",
      "#СвинговаяТорговля",
      "#Цикличность",
      "#ТехническийАнализ",
      "#ЛинияДействия",
      "#Основа",
      "#РазворотнаяЗона",
      "#Вилы",
      "#Синтез",
      "#СрединнаяЛиния",
      "#WarningLines",
      "#Время",
      "#ГоризонтальныеУровни",
      "#НовыеВилы",
      "#Медиана",
      "#ДействиеРеакция",
      "#A",
      "#СигнальныеЛинии",
      "#Стратегия",
      "#МетодЭндрюса",
      "#Тренд",
      "#СуперВилы"
    ],
    "links": [],
    "chunk_index": 2,
    "total_chunks": 4,
    "title": "📅-timeline"
  },
  {
    "id": "indexes/📅-timeline.md::3",
    "source": "indexes/📅-timeline.md",
    "content": "#СрединнаяЛиния #Стратегия #СуперВилы #ТехническийАнализ #ТорговляПоМедиане #Тренд #Цикличность",
    "tags": [
      "#ТорговляПоМедиане",
      "#ЛинияЦентра",
      "#ПредупреждающиеЛинии",
      "#Pitchfork",
      "#MomentumSwing",
      "#Микула",
      "#СвинговаяТорговля",
      "#Цикличность",
      "#ТехническийАнализ",
      "#ЛинияДействия",
      "#Основа",
      "#РазворотнаяЗона",
      "#Вилы",
      "#Синтез",
      "#СрединнаяЛиния",
      "#WarningLines",
      "#Время",
      "#ГоризонтальныеУровни",
      "#НовыеВилы",
      "#Медиана",
      "#ДействиеРеакция",
      "#A",
      "#СигнальныеЛинии",
      "#Стратегия",
      "#МетодЭндрюса",
      "#Тренд",
      "#СуперВилы"
    ],
    "links": [],
    "chunk_index": 3,
    "total_chunks": 4,
    "title": "📅-timeline"
  },
  {
    "id": "indexes/🏷️-tags.md::0",
    "source": "indexes/🏷️-tags.md",
    "content": "# Tags Index: Методы Эндрюса ## #КонцепцииОсновы - [[001-median-line|📐 Срединная линия]] — магнит цены, 80% возвратов - [[002-pitchfork|📊 Вилы Эндрюса]] — структура канала - [[003-signal-lines|📶 Сигнальные линии]] — пробои параллелей ## #МетодыДействияРеакции - [[031-ar1-linea-centro|① Метод A-R 1: Линия Центра]] - [[041-ar2-action-line|② Метод A-R 2: Линия Действия]] - [[092-ar3-horizontal|③ Метод A-R 3: Горизонтальные уровни]] ## #МодификацииВил - [[054-new-forks-rule1|🔧 Новые Вилы: Правило 1]] -",
    "tags": [
      "#QQQ",
      "#Вход",
      "#SLB",
      "#NVLS",
      "#AXP",
      "#Брокер",
      "#Медиа",
      "#Индекс",
      "#Полувилы",
      "#МодификацииВил",
      "#SPLS",
      "#СвечныеПаттерны",
      "#ПараллельныеЛинии",
      "#Ритейл",
      "#VRSN",
      "#CMCSA",
      "#Безопасность",
      "#NITE",
      "#ТорговыеСтратегии",
      "#Банк",
      "#Телеком",
      "#CSCO",
      "#Полупроводники",
      "#Цикличность",
      "#JNJ",
      "#QCOM",
      "#Фарма",
      "#Домены",
      "#Нефть",
      "#RNWK",
      "#РазворотнаяЗона",
      "#SPX",
      "#Вилы",
      "#ТегиПоАспектам",
      "#КонцепцииОсновы",
      "#Углы",
      "#ВременныеОкна",
      "#Дивергенция",
      "#СрединнаяЛиния",
      "#ПримерыНаРеальныхАктивах",
      "#Подтверждение",
      "#Техно",
      "#MOT",
      "#Цель",
      "#MER",
      "#Гостиницы",
      "#RD",
      "#TLAB",
      "#TXN",
      "#MAR",
      "#Сопротивление",
      "#Стоп",
      "#Поддержка",
      "#JPM",
      "#LLY",
      "#ДэйТрейдинг",
      "#BOFI",
      "#Кабельное",
      "#NET",
      "#МетодыДействияРеакции",
      "#Финансы",
      "#Momentum",
      "#Тренд",
      "#СуперВилы"
    ],
    "links": [
      "001-median-line",
      "002-pitchfork",
      "003-signal-lines",
      "031-ar1-linea-centro",
      "041-ar2-action-line",
      "092-ar3-horizontal",
      "054-new-forks-rule1",
      "080-median-pivot-zone",
      "095-super-pitchforks",
      "momentum-swing",
      "high-low-lines"
    ],
    "chunk_index": 0,
    "total_chunks": 5,
    "title": "🏷️-tags"
  },
  {
    "id": "indexes/🏷️-tags.md::1",
    "source": "indexes/🏷️-tags.md",
    "content": "[[080-median-pivot-zone|⏱️ Разворотная Зона Срединной Линии]] - [[095-super-pitchforks|🚀 Супер-Вилы]] ## #ТорговыеСтратегии - [[momentum-swing|📈 Momentum Swing]] - [[high-low-lines|📉 Линии High-High и Low-Low]] ## #ПримерыНаРеальныхАктивах | Актив | Метод | Теги | |-------|-------|------| | Qualcomm (QCOM) | Супервилы | `#QCOM` `#СуперВилы` | | J.P. Morgan | Разворотная Зона, Momentum Swing | `#JPM` `#РазворотнаяЗона` | | S&P 500 | Momentum Swing, Разворотная Зона | `#SPX` `#Индекс` | | Eli Lilly |",
    "tags": [
      "#QQQ",
      "#Вход",
      "#SLB",
      "#NVLS",
      "#AXP",
      "#Брокер",
      "#Медиа",
      "#Индекс",
      "#Полувилы",
      "#МодификацииВил",
      "#SPLS",
      "#СвечныеПаттерны",
      "#ПараллельныеЛинии",
      "#Ритейл",
      "#VRSN",
      "#CMCSA",
      "#Безопасность",
      "#NITE",
      "#ТорговыеСтратегии",
      "#Банк",
      "#Телеком",
      "#CSCO",
      "#Полупроводники",
      "#Цикличность",
      "#JNJ",
      "#QCOM",
      "#Фарма",
      "#Домены",
      "#Нефть",
      "#RNWK",
      "#РазворотнаяЗона",
      "#SPX",
      "#Вилы",
      "#ТегиПоАспектам",
      "#КонцепцииОсновы",
      "#Углы",
      "#ВременныеОкна",
      "#Дивергенция",
      "#СрединнаяЛиния",
      "#ПримерыНаРеальныхАктивах",
      "#Подтверждение",
      "#Техно",
      "#MOT",
      "#Цель",
      "#MER",
      "#Гостиницы",
      "#RD",
      "#TLAB",
      "#TXN",
      "#MAR",
      "#Сопротивление",
      "#Стоп",
      "#Поддержка",
      "#JPM",
      "#LLY",
      "#ДэйТрейдинг",
      "#BOFI",
      "#Кабельное",
      "#NET",
      "#МетодыДействияРеакции",
      "#Финансы",
      "#Momentum",
      "#Тренд",
      "#СуперВилы"
    ],
    "links": [
      "001-median-line",
      "002-pitchfork",
      "003-signal-lines",
      "031-ar1-linea-centro",
      "041-ar2-action-line",
      "092-ar3-horizontal",
      "054-new-forks-rule1",
      "080-median-pivot-zone",
      "095-super-pitchforks",
      "momentum-swing",
      "high-low-lines"
    ],
    "chunk_index": 1,
    "total_chunks": 5,
    "title": "🏷️-tags"
  },
  {
    "id": "indexes/🏷️-tags.md::2",
    "source": "indexes/🏷️-tags.md",
    "content": "Супервилы | `#LLY` `#Фарма` | | Eli Lilly | Momentum Swing | `#LLY` `#Momentum` | | Motorola | 50% Вилы | `#MOT` `#Полувилы` | | Cisco Systems | 50% Вилы | `#CSCO` `#Техно` | | Texas Instruments | 50% Вилы | `#TXN` `#Полувилы` | | Bank One | 50% Вилы | `#BOFI` `#Банк` | | Schlumberger | Предупреждающие линии | `#SLB` `#Нефть` | | Verisign | 50% Вилы + Warning Lines | `#VRSN` `#Домены` | | Novellus Systems | 50% Вилы | `#NVLS` `#Полупроводники` | | Network Associates | Супервилы | `#NET` `#Безопасность` | |",
    "tags": [
      "#QQQ",
      "#Вход",
      "#SLB",
      "#NVLS",
      "#AXP",
      "#Брокер",
      "#Медиа",
      "#Индекс",
      "#Полувилы",
      "#МодификацииВил",
      "#SPLS",
      "#СвечныеПаттерны",
      "#ПараллельныеЛинии",
      "#Ритейл",
      "#VRSN",
      "#CMCSA",
      "#Безопасность",
      "#NITE",
      "#ТорговыеСтратегии",
      "#Банк",
      "#Телеком",
      "#CSCO",
      "#Полупроводники",
      "#Цикличность",
      "#JNJ",
      "#QCOM",
      "#Фарма",
      "#Домены",
      "#Нефть",
      "#RNWK",
      "#РазворотнаяЗона",
      "#SPX",
      "#Вилы",
      "#ТегиПоАспектам",
      "#КонцепцииОсновы",
      "#Углы",
      "#ВременныеОкна",
      "#Дивергенция",
      "#СрединнаяЛиния",
      "#ПримерыНаРеальныхАктивах",
      "#Подтверждение",
      "#Техно",
      "#MOT",
      "#Цель",
      "#MER",
      "#Гостиницы",
      "#RD",
      "#TLAB",
      "#TXN",
      "#MAR",
      "#Сопротивление",
      "#Стоп",
      "#Поддержка",
      "#JPM",
      "#LLY",
      "#ДэйТрейдинг",
      "#BOFI",
      "#Кабельное",
      "#NET",
      "#МетодыДействияРеакции",
      "#Финансы",
      "#Momentum",
      "#Тренд",
      "#СуперВилы"
    ],
    "links": [
      "001-median-line",
      "002-pitchfork",
      "003-signal-lines",
      "031-ar1-linea-centro",
      "041-ar2-action-line",
      "092-ar3-horizontal",
      "054-new-forks-rule1",
      "080-median-pivot-zone",
      "095-super-pitchforks",
      "momentum-swing",
      "high-low-lines"
    ],
    "chunk_index": 2,
    "total_chunks": 5,
    "title": "🏷️-tags"
  },
  {
    "id": "indexes/🏷️-tags.md::3",
    "source": "indexes/🏷️-tags.md",
    "content": "Knight Trading | Линии 0-4, Супервилы | `#NITE` `#ДэйТрейдинг` | | Comcast | Супервилы | `#CMCSA` `#Кабельное` | | Staples | Супервилы | `#SPLS` `#Ритейл` | | Merrill Lynch | Разворотная Зона, Momentum Swing | `#MER` `#Брокер` | | Johnson & Johnson | Разворотная Зона, Momentum Swing | `#JNJ` `#Фарма` | | Tellabs | Разворотная Зона | `#TLAB` `#Телеком` | | Royal Dutch Petroleum | Momentum Swing, Новые Вилы | `#RD` `#Нефть` | | Real Networks | Новые Вилы Правило 1 | `#RNWK` `#Медиа` | | American Express | 50%",
    "tags": [
      "#QQQ",
      "#Вход",
      "#SLB",
      "#NVLS",
      "#AXP",
      "#Брокер",
      "#Медиа",
      "#Индекс",
      "#Полувилы",
      "#МодификацииВил",
      "#SPLS",
      "#СвечныеПаттерны",
      "#ПараллельныеЛинии",
      "#Ритейл",
      "#VRSN",
      "#CMCSA",
      "#Безопасность",
      "#NITE",
      "#ТорговыеСтратегии",
      "#Банк",
      "#Телеком",
      "#CSCO",
      "#Полупроводники",
      "#Цикличность",
      "#JNJ",
      "#QCOM",
      "#Фарма",
      "#Домены",
      "#Нефть",
      "#RNWK",
      "#РазворотнаяЗона",
      "#SPX",
      "#Вилы",
      "#ТегиПоАспектам",
      "#КонцепцииОсновы",
      "#Углы",
      "#ВременныеОкна",
      "#Дивергенция",
      "#СрединнаяЛиния",
      "#ПримерыНаРеальныхАктивах",
      "#Подтверждение",
      "#Техно",
      "#MOT",
      "#Цель",
      "#MER",
      "#Гостиницы",
      "#RD",
      "#TLAB",
      "#TXN",
      "#MAR",
      "#Сопротивление",
      "#Стоп",
      "#Поддержка",
      "#JPM",
      "#LLY",
      "#ДэйТрейдинг",
      "#BOFI",
      "#Кабельное",
      "#NET",
      "#МетодыДействияРеакции",
      "#Финансы",
      "#Momentum",
      "#Тренд",
      "#СуперВилы"
    ],
    "links": [
      "001-median-line",
      "002-pitchfork",
      "003-signal-lines",
      "031-ar1-linea-centro",
      "041-ar2-action-line",
      "092-ar3-horizontal",
      "054-new-forks-rule1",
      "080-median-pivot-zone",
      "095-super-pitchforks",
      "momentum-swing",
      "high-low-lines"
    ],
    "chunk_index": 3,
    "total_chunks": 5,
    "title": "🏷️-tags"
  },
  {
    "id": "indexes/🏷️-tags.md::4",
    "source": "indexes/🏷️-tags.md",
    "content": "Вилы | `#AXP` `#Финансы` | | Marriott | Метод A-R 3 | `#MAR` `#Гостиницы` | | NASDAQ 100 | Метод A-R 3 | `#QQQ` `#Индекс` | ## #ТегиПоАспектам ### Геометрия `#СрединнаяЛиния` `#Вилы` `#ПараллельныеЛинии` `#Углы` ### Время `#РазворотнаяЗона` `#Цикличность` `#ВременныеОкна` ### Торговля `#Вход` `#Стоп` `#Цель` `#Подтверждение` `#СвечныеПаттерны` ### Анализ `#Тренд` `#Поддержка` `#Сопротивление` `#Дивергенция`",
    "tags": [
      "#QQQ",
      "#Вход",
      "#SLB",
      "#NVLS",
      "#AXP",
      "#Брокер",
      "#Медиа",
      "#Индекс",
      "#Полувилы",
      "#МодификацииВил",
      "#SPLS",
      "#СвечныеПаттерны",
      "#ПараллельныеЛинии",
      "#Ритейл",
      "#VRSN",
      "#CMCSA",
      "#Безопасность",
      "#NITE",
      "#ТорговыеСтратегии",
      "#Банк",
      "#Телеком",
      "#CSCO",
      "#Полупроводники",
      "#Цикличность",
      "#JNJ",
      "#QCOM",
      "#Фарма",
      "#Домены",
      "#Нефть",
      "#RNWK",
      "#РазворотнаяЗона",
      "#SPX",
      "#Вилы",
      "#ТегиПоАспектам",
      "#КонцепцииОсновы",
      "#Углы",
      "#ВременныеОкна",
      "#Дивергенция",
      "#СрединнаяЛиния",
      "#ПримерыНаРеальныхАктивах",
      "#Подтверждение",
      "#Техно",
      "#MOT",
      "#Цель",
      "#MER",
      "#Гостиницы",
      "#RD",
      "#TLAB",
      "#TXN",
      "#MAR",
      "#Сопротивление",
      "#Стоп",
      "#Поддержка",
      "#JPM",
      "#LLY",
      "#ДэйТрейдинг",
      "#BOFI",
      "#Кабельное",
      "#NET",
      "#МетодыДействияРеакции",
      "#Финансы",
      "#Momentum",
      "#Тренд",
      "#СуперВилы"
    ],
    "links": [
      "001-median-line",
      "002-pitchfork",
      "003-signal-lines",
      "031-ar1-linea-centro",
      "041-ar2-action-line",
      "092-ar3-horizontal",
      "054-new-forks-rule1",
      "080-median-pivot-zone",
      "095-super-pitchforks",
      "momentum-swing",
      "high-low-lines"
    ],
    "chunk_index": 4,
    "total_chunks": 5,
    "title": "🏷️-tags"
  }
]